shaper/__init__.py
shaper/_version.py
shaper/cli.py
shaper/manager.py
shaper/renderer.py
shaper/utils.py
shaper/libs/__init__.py
shaper/libs/dicttoxml.py
shaper/libs/loader.py
shaper/libs/parser.py
tests/__init__.py
tests/conftest.py
tests/test_manager.py
tests/test_shaper.py
shaper-0.1.3.dist-info/LICENSE
shaper-0.1.3.dist-info/METADATA
shaper-0.1.3.dist-info/WHEEL
shaper-0.1.3.dist-info/entry_points.txt
shaper-0.1.3.dist-info/top_level.txt
shaper-0.1.3.dist-info/RECORD
