Metadata-Version: 2.1
Name: shaper
Version: 0.1.3
Summary: Manage application options
Home-page: https://github.com/arno49/shaper/wiki
Author: Ivan Bogomazov
Author-email: ivan.bogomazov@gmail.com
License: UNKNOWN
Platform: UNKNOWN
Classifier: Environment :: Console
Classifier: Intended Audience :: Developers
Classifier: Operating System :: OS Independent
Classifier: Programming Language :: Python :: 2.7
Classifier: Programming Language :: Python :: 3.5
Classifier: Topic :: Utilities
Classifier: License :: OSI Approved :: Apache Software License
Requires-Dist: Jinja2 (==2.10)
Requires-Dist: pyyaml (==3.13)
Requires-Dist: versioneer (==0.18)
Requires-Dist: xmltodict (==0.11.0)
Requires-Dist: path.py (==11.5.0)
Provides-Extra: test
Requires-Dist: pytest (==3.0.0) ; extra == 'test'
Requires-Dist: mock (==2.0.0) ; extra == 'test'
Requires-Dist: pylint (==1.9.3) ; extra == 'test'
Requires-Dist: pep8 (==1.7.0) ; extra == 'test'
Requires-Dist: tox (==2.5.0) ; extra == 'test'
Requires-Dist: codecov (>=1.4.0) ; extra == 'test'
Requires-Dist: pytest-cov (==2.6.0) ; extra == 'test'
